abstra_json_sql/__init__.py
abstra_json_sql/apply.py
abstra_json_sql/apply_test.py
abstra_json_sql/ast.py
abstra_json_sql/ast_utils.py
abstra_json_sql/authorization.py
abstra_json_sql/authorization_test.py
abstra_json_sql/cli.py
abstra_json_sql/eval.py
abstra_json_sql/eval_test.py
abstra_json_sql/field_name.py
abstra_json_sql/infer.py
abstra_json_sql/infer_test.py
abstra_json_sql/lexer.py
abstra_json_sql/lexer_test.py
abstra_json_sql/parser.py
abstra_json_sql/parser_test.py
abstra_json_sql/string_utils.py
abstra_json_sql/string_utils_test.py
abstra_json_sql/tables.py
abstra_json_sql/tables_test.py
abstra_json_sql/tokens.py
abstra_json_sql/persistence/__init__.py
abstra_json_sql/persistence/base_test.py
abstra_json_sql/persistence/extended.py
abstra_json_sql/persistence/extended_test.py
abstra_json_sql/persistence/json.py
abstra_json_sql/persistence/json_test.py
abstra_json_sql/persistence/jsonl.py
abstra_json_sql/persistence/jsonl_test.py
abstra_json_sql/persistence/memory.py
abstra_json_sql/persistence/memory_test.py
abstra_json_sql-0.0.14.dist-info/METADATA
abstra_json_sql-0.0.14.dist-info/WHEEL
abstra_json_sql-0.0.14.dist-info/entry_points.txt
abstra_json_sql-0.0.14.dist-info/top_level.txt
abstra_json_sql-0.0.14.dist-info/RECORD
