Metadata-Version: 2.1
Name: abstra-json-sql
Version: 0.0.14
Summary: run SQL queries on JSON data
Home-page: https://github.com/abstra-app/json-sql
Author: Abstra
Author-email: help@abstra.app
License: MIT
Platform: UNKNOWN
Requires-Python: >=3.8, <4
Requires-Dist: pydantic>=2.0.0
